tmax_ims/__init__.py
tmax_ims/bot.py
tmax_ims/ims.py
tmax_ims-0.0.3.dist-info/LICENSE
tmax_ims-0.0.3.dist-info/METADATA
tmax_ims-0.0.3.dist-info/WHEEL
tmax_ims-0.0.3.dist-info/top_level.txt
tmax_ims-0.0.3.dist-info/RECORD
