Metadata-Version: 2.1
Name: tmax-ims
Version: 0.0.3
Summary: TMAX IMS issue alert package
Home-page: https://github.com/ZeroStrength/tmax_ims
Author: Changyun Lee
Author-email: brownbearpower@gmail.com
License: UNKNOWN
Platform: UNKNOWN
Classifier: Programming Language :: Python :: 3
Classifier: License :: OSI Approved :: MIT License
Classifier: Operating System :: OS Independent
Requires-Python: >=3.6
Requires-Dist: bs4
Requires-Dist: py-notifier
Requires-Dist: pandas
Requires-Dist: requests
